{
  "type": "series",
  "name": "Detective D.D. Warren",
  "slug": "detective-d-d-warren",
  "source": "https://www.orderofbooks.com/characters/detective-dd-warren/",
  "image": "https://www.orderofbooks.com/wp-content/uploads/2012/03/Detective-DD-Warren.jpg",
  "books": [
    {
      "title": "Alone",
      "year": 2004,
      "links": {
        "amazon_es": ""
      },
      "index": 1
    },
    {
      "title": "Hide",
      "year": 2007,
      "links": {
        "amazon_es": ""
      },
      "index": 2
    },
    {
      "title": "The Neighbor",
      "year": 2009,
      "links": {
        "amazon_es": ""
      },
      "index": 3
    },
    {
      "title": "Live to Tell",
      "year": 2010,
      "links": {
        "amazon_es": ""
      },
      "index": 4
    },
    {
      "title": "Love You More",
      "year": 2011,
      "links": {
        "amazon_es": ""
      },
      "index": 5
    },
    {
      "title": "Catch Me",
      "year": 2012,
      "links": {
        "amazon_es": ""
      },
      "index": 6
    },
    {
      "title": "Fear Nothing",
      "year": 2014,
      "links": {
        "amazon_es": ""
      },
      "index": 7
    },
    {
      "title": "Find Her",
      "year": 2016,
      "links": {
        "amazon_es": ""
      },
      "index": 8
    },
    {
      "title": "Look For Me",
      "year": 2018,
      "links": {
        "amazon_es": ""
      },
      "index": 9
    },
    {
      "title": "The Guy Who Died Twice",
      "year": 2019,
      "links": {
        "amazon_es": ""
      },
      "index": 10
    },
    {
      "title": "Never Tell",
      "year": 2019,
      "links": {
        "amazon_es": ""
      },
      "index": 11
    },
    {
      "title": "When You See Me",
      "year": 2020,
      "links": {
        "amazon_es": ""
      },
      "index": 12
    }
  ]
}