{
  "type": "series",
  "name": "Paranormals",
  "slug": "paranormals",
  "source": "https://www.orderofbooks.com/characters/paranormals/",
  "image": "https://www.orderofbooks.com/wp-content/uploads/2016/04/The-Paranormals-by-JL-Bryan-500x200.jpg",
  "authors": [
    {
      "name": "JL Bryan",
      "slug": "jl-bryan"
    }
  ],
  "books": [
    {
      "title": "Jenny Pox",
      "year": 2010,
      "links": {
        "amazon_es": ""
      },
      "index": 1
    },
    {
      "title": "Tommy Nightmare",
      "year": 2011,
      "links": {
        "amazon_es": ""
      },
      "index": 2
    },
    {
      "title": "Alexander Death",
      "year": 2011,
      "links": {
        "amazon_es": ""
      },
      "index": 3
    },
    {
      "title": "Jenny Plague-Bringer",
      "year": 2012,
      "links": {
        "amazon_es": ""
      },
      "index": 4
    }
  ]
}