{
  "type": "series",
  "name": "Roy Grace",
  "slug": "roy-grace",
  "source": "https://www.orderofbooks.com/characters/roy-grace/",
  "image": "https://www.orderofbooks.com/wp-content/uploads/2012/03/Roy-Grace.jpg",
  "books": [
    {
      "title": "Dead Simple",
      "year": 2005,
      "links": {
        "amazon_es": ""
      },
      "index": 1
    },
    {
      "title": "Looking Good Dead",
      "year": 2006,
      "links": {
        "amazon_es": ""
      },
      "index": 2
    },
    {
      "title": "Not Dead Enough",
      "year": 2007,
      "links": {
        "amazon_es": ""
      },
      "index": 3
    },
    {
      "title": "Dead Man's Footsteps",
      "year": 2008,
      "links": {
        "amazon_es": ""
      },
      "index": 4
    },
    {
      "title": "Dead Tomorrow",
      "year": 2009,
      "links": {
        "amazon_es": ""
      },
      "index": 5
    },
    {
      "title": "Dead Like You",
      "year": 2010,
      "links": {
        "amazon_es": ""
      },
      "index": 6
    },
    {
      "title": "Dead Man's Grip",
      "year": 2011,
      "links": {
        "amazon_es": ""
      },
      "index": 7
    },
    {
      "title": "Not Dead Yet",
      "year": 2012,
      "links": {
        "amazon_es": ""
      },
      "index": 8
    },
    {
      "title": "Dead Man's Time",
      "year": 2013,
      "links": {
        "amazon_es": ""
      },
      "index": 9
    },
    {
      "title": "Want You Dead",
      "year": 2014,
      "links": {
        "amazon_es": ""
      },
      "index": 10
    },
    {
      "title": "You Are Dead",
      "year": 2015,
      "links": {
        "amazon_es": ""
      },
      "index": 11
    },
    {
      "title": "Love You Dead",
      "year": 2016,
      "links": {
        "amazon_es": ""
      },
      "index": 12
    },
    {
      "title": "Need You Dead",
      "year": 2017,
      "links": {
        "amazon_es": ""
      },
      "index": 13
    },
    {
      "title": "Dead If You Don't",
      "year": 2018,
      "links": {
        "amazon_es": ""
      },
      "index": 14
    },
    {
      "title": "Dead at First Sight",
      "year": 2019,
      "links": {
        "amazon_es": ""
      },
      "index": 15
    },
    {
      "title": "Find Them Dead",
      "year": 2020,
      "links": {
        "amazon_es": ""
      },
      "index": 16
    },
    {
      "title": "Left You Dead",
      "year": 2021,
      "links": {
        "amazon_es": ""
      },
      "index": 17
    },
    {
      "title": "Picture You Dead",
      "year": 2022,
      "links": {
        "amazon_es": ""
      },
      "index": 18
    },
    {
      "title": "Stop Them Dead",
      "year": 2023,
      "links": {
        "amazon_es": ""
      },
      "index": 19
    },
    {
      "title": "They Thought I Was Dead: Sandy's Story",
      "year": 2024,
      "links": {
        "amazon_es": ""
      },
      "index": 20
    },
    {
      "title": "One of Us Is Dead",
      "year": 2024,
      "links": {
        "amazon_es": ""
      },
      "index": 21
    }
  ]
}