{
  "type": "series",
  "name": "Ryan Lock",
  "slug": "ryan-lock",
  "source": "https://www.orderofbooks.com/characters/ryan-lock/",
  "image": "https://www.orderofbooks.com/wp-content/uploads/2014/10/Ryan-Lock-by-Sean-Black-551x200.jpg",
  "authors": [
    {
      "name": "Sean Black",
      "slug": "sean-black"
    }
  ],
  "books": [
    {
      "title": "Lockdown",
      "year": 2009,
      "links": {
        "amazon_es": ""
      },
      "index": 1
    },
    {
      "title": "Deadlock",
      "year": 2010,
      "links": {
        "amazon_es": ""
      },
      "index": 2
    },
    {
      "title": "Grid Lock",
      "year": 2011,
      "links": {
        "amazon_es": ""
      },
      "index": 3
    },
    {
      "title": "The Devil's Bounty",
      "year": 2012,
      "links": {
        "amazon_es": ""
      },
      "index": 4
    },
    {
      "title": "Lock & Load",
      "year": 2012,
      "links": {
        "amazon_es": ""
      },
      "index": 5
    },
    {
      "title": "The Innocent",
      "year": 2014,
      "links": {
        "amazon_es": ""
      },
      "index": 6
    },
    {
      "title": "Fire Point",
      "year": 2014,
      "links": {
        "amazon_es": ""
      },
      "index": 7
    },
    {
      "title": "Budapest/48",
      "year": 2015,
      "links": {
        "amazon_es": ""
      },
      "index": 8
    },
    {
      "title": "The Edge of Alone",
      "year": 2016,
      "links": {
        "amazon_es": ""
      },
      "index": 9
    },
    {
      "title": "Second Chance",
      "year": 2017,
      "links": {
        "amazon_es": ""
      },
      "index": 10
    },
    {
      "title": "Red Tiger",
      "year": 2018,
      "links": {
        "amazon_es": ""
      },
      "index": 11
    },
    {
      "title": "The Deep Abiding",
      "year": 2019,
      "links": {
        "amazon_es": ""
      },
      "index": 12
    },
    {
      "title": "Avenue of Thieves",
      "year": 2020,
      "links": {
        "amazon_es": ""
      },
      "index": 13
    },
    {
      "title": "The Last Bodyguard",
      "year": 2021,
      "links": {
        "amazon_es": ""
      },
      "index": 14
    },
    {
      "title": "The Yacht Girl",
      "year": 2025,
      "links": {
        "amazon_es": ""
      },
      "index": 15
    }
  ]
}