{
  "type": "series",
  "name": "Soul Screamers",
  "slug": "soul-screamers",
  "source": "https://www.orderofbooks.com/characters/soul-screamers/",
  "image": "https://www.orderofbooks.com/wp-content/uploads/2015/11/Soul-Screamers-by-Rachel-Vincent-500x200.jpg",
  "authors": [
    {
      "name": "Rachel Vincent",
      "slug": "rachel-vincent"
    }
  ],
  "books": [
    {
      "title": "My Soul to Lose",
      "year": 2009,
      "links": {
        "amazon_es": ""
      },
      "index": 1
    },
    {
      "title": "My Soul to Take",
      "year": 2009,
      "links": {
        "amazon_es": ""
      },
      "index": 2
    },
    {
      "title": "My Soul to Save",
      "year": 2009,
      "links": {
        "amazon_es": ""
      },
      "index": 3
    },
    {
      "title": "Fearless",
      "year": 2010,
      "links": {
        "amazon_es": ""
      },
      "index": 4
    },
    {
      "title": "My Soul to Keep",
      "year": 2010,
      "links": {
        "amazon_es": ""
      },
      "index": 5
    },
    {
      "title": "Reaper",
      "year": 2010,
      "links": {
        "amazon_es": ""
      },
      "index": 6
    },
    {
      "title": "My Soul to Steal",
      "year": 2010,
      "links": {
        "amazon_es": ""
      },
      "index": 7
    },
    {
      "title": "Niederwald",
      "year": 2011,
      "links": {
        "amazon_es": ""
      },
      "index": 8
    },
    {
      "title": "If I Die",
      "year": 2011,
      "links": {
        "amazon_es": ""
      },
      "index": 9
    },
    {
      "title": "Never to Sleep",
      "year": 2012,
      "links": {
        "amazon_es": ""
      },
      "index": 10
    },
    {
      "title": "Before I Wake",
      "year": 2012,
      "links": {
        "amazon_es": ""
      },
      "index": 11
    },
    {
      "title": "With All My Soul",
      "year": 2013,
      "links": {
        "amazon_es": ""
      },
      "index": 12
    },
    {
      "title": "Last Request",
      "year": 2014,
      "links": {
        "amazon_es": ""
      },
      "index": 13
    }
  ]
}