{
  "type": "series",
  "name": "Wimpy Kid",
  "slug": "wimpy-kid",
  "source": "https://www.orderofbooks.com/characters/diary-of-a-wimpy-kid/",
  "image": "https://www.orderofbooks.com/wp-content/uploads/2011/08/Diary-of-a-Wimpy-Kid.jpg",
  "books": [
    {
      "title": "Diary of a Wimpy Kid",
      "year": 2007,
      "links": {
        "amazon_es": ""
      },
      "index": 1
    },
    {
      "title": "Rodrick Rules",
      "year": 2008,
      "links": {
        "amazon_es": ""
      },
      "index": 2
    },
    {
      "title": "The Last Straw",
      "year": 2009,
      "links": {
        "amazon_es": ""
      },
      "index": 3
    },
    {
      "title": "Dog Days",
      "year": 2009,
      "links": {
        "amazon_es": ""
      },
      "index": 4
    },
    {
      "title": "The Ugly Truth",
      "year": 2010,
      "links": {
        "amazon_es": ""
      },
      "index": 5
    },
    {
      "title": "Cabin Fever",
      "year": 2010,
      "links": {
        "amazon_es": ""
      },
      "index": 6
    },
    {
      "title": "The Third Wheel",
      "year": 2012,
      "links": {
        "amazon_es": ""
      },
      "index": 7
    },
    {
      "title": "Hard Luck",
      "year": 2013,
      "links": {
        "amazon_es": ""
      },
      "index": 8
    },
    {
      "title": "The Long Haul",
      "year": 2014,
      "links": {
        "amazon_es": ""
      },
      "index": 9
    },
    {
      "title": "Old School",
      "year": 2015,
      "links": {
        "amazon_es": ""
      },
      "index": 10
    },
    {
      "title": "Double Down",
      "year": 2016,
      "links": {
        "amazon_es": ""
      },
      "index": 11
    },
    {
      "title": "The Getaway",
      "year": 2017,
      "links": {
        "amazon_es": ""
      },
      "index": 12
    },
    {
      "title": "The Meltdown",
      "year": 2018,
      "links": {
        "amazon_es": ""
      },
      "index": 13
    },
    {
      "title": "Wrecking Ball",
      "year": 2019,
      "links": {
        "amazon_es": ""
      },
      "index": 14
    },
    {
      "title": "The Deep End",
      "year": 2020,
      "links": {
        "amazon_es": ""
      },
      "index": 15
    },
    {
      "title": "Big Shot",
      "year": 2021,
      "links": {
        "amazon_es": ""
      },
      "index": 16
    },
    {
      "title": "Diper Överlöde",
      "year": 2022,
      "links": {
        "amazon_es": ""
      },
      "index": 17
    },
    {
      "title": "No Brainer",
      "year": 2023,
      "links": {
        "amazon_es": ""
      },
      "index": 18
    },
    {
      "title": "Hot Mess",
      "year": 2024,
      "links": {
        "amazon_es": ""
      },
      "index": 19
    },
    {
      "title": "Partypooper",
      "year": 2025,
      "links": {
        "amazon_es": ""
      },
      "index": 20
    }
  ]
}